certbot_dns_eurodns/__init__.py
certbot_dns_eurodns/dns_eurodns.py
certbot_dns_eurodns-1.8.1.dist-info/LICENSE.txt
certbot_dns_eurodns-1.8.1.dist-info/METADATA
certbot_dns_eurodns-1.8.1.dist-info/WHEEL
certbot_dns_eurodns-1.8.1.dist-info/entry_points.txt
certbot_dns_eurodns-1.8.1.dist-info/top_level.txt
certbot_dns_eurodns-1.8.1.dist-info/RECORD
